basecamper/.DS_Store
basecamper/__init__.py
basecamper/basecamper.py
basecamper/grain/README.md
basecamper/grain/__init__.py
basecamper/grain/grain.py
basecamper/loss/__init__.py
basecamper/loss/dice.py
basecamper/loss/dice_spline.py
basecamper/loss/focal.py
basecamper/loss/jaccard.py
basecamper/loss/spline.py
basecamper/loss/tversky.py
basecamper/metrics/.DS_Store
basecamper/metrics/README.md
basecamper/metrics/__init__.py
basecamper/metrics/metrics.py
basecamper/runner/README.md
basecamper/runner/__init__.py
basecamper/runner/runner.py
basecamper-0.10.55.dist-info/LICENSE
basecamper-0.10.55.dist-info/WHEEL
basecamper-0.10.55.dist-info/METADATA
basecamper-0.10.55.dist-info/RECORD
