Metadata-Version: 2.1
Name: basecamper
Version: 0.10.55
Summary: Training utility library and config manager for Granular Machine Vision research
Home-page: https://github.com/granularai/basecamper
License: MIT
Author: Sagar Verma
Author-email: sagar@granular.ai
Requires-Python: >=3.6.1,<4.0.0
Classifier: Intended Audience :: Developers
Classifier: License :: OSI Approved :: MIT License
Classifier: Natural Language :: English
Classifier: Programming Language :: Python :: 3
Classifier: Programming Language :: Python :: 3.6
Classifier: Programming Language :: Python :: 3.7
Classifier: Programming Language :: Python :: 3.8
Requires-Dist: arrow (>=0.16.0,<0.17.0)
Requires-Dist: cookiecutter (>=1.7.2,<2.0.0)
Requires-Dist: pytest (>=6.0.2,<7.0.0)
Project-URL: Repository, https://github.com/granularai/basecamper
